vsync/__init__.py
vsync/vsync.py
vsync/vsync_dal.py
vsync-1.0.1.dist-info/LICENSE
vsync-1.0.1.dist-info/METADATA
vsync-1.0.1.dist-info/WHEEL
vsync-1.0.1.dist-info/entry_points.txt
vsync-1.0.1.dist-info/top_level.txt
vsync-1.0.1.dist-info/RECORD
