Metadata-Version: 2.1
Name: vsync
Version: 1.0.1
Summary: A tool to sync data between dissimilar Vertica clusters
Home-page: https://gitlab.com/vsync/vsync
Author: Yahel Agassi
Author-email: yahel2410@gmail.com
License: UNKNOWN
Platform: UNKNOWN
Classifier: Programming Language :: Python :: 2.7
Classifier: License :: OSI Approved :: GNU General Public License v3 (GPLv3)
Classifier: Operating System :: OS Independent
Requires-Dist: pyodbc
Requires-Dist: click (>=7)
Requires-Dist: configparser
